aiida_gaussian/__init__.py
aiida_gaussian/version.py
aiida_gaussian/calculations/__init__.py
aiida_gaussian/calculations/cubegen.py
aiida_gaussian/calculations/formchk.py
aiida_gaussian/calculations/gaussian.py
aiida_gaussian/parsers/__init__.py
aiida_gaussian/parsers/cubegen.py
aiida_gaussian/parsers/gaussian.py
aiida_gaussian/utils/__init__.py
aiida_gaussian/utils/cube.py
aiida_gaussian/workchains/__init__.py
aiida_gaussian/workchains/base.py
aiida_gaussian/workchains/cubes.py
tests/__init__.py
tests/conftest.py
tests/data/__init__.py
aiida_gaussian-2.2.0.dist-info/LICENSE
aiida_gaussian-2.2.0.dist-info/METADATA
aiida_gaussian-2.2.0.dist-info/WHEEL
aiida_gaussian-2.2.0.dist-info/entry_points.txt
aiida_gaussian-2.2.0.dist-info/top_level.txt
aiida_gaussian-2.2.0.dist-info/RECORD
