Metadata-Version: 2.1
Name: aiida-gaussian
Version: 2.2.0
Summary: AiiDA plugin for the Gaussian quantum chemistry software.
Author: Kristjan Eimre, Pezhman Zarabadi-Poor, Aliaksandr Yakutovich
License: MIT
Project-URL: Homepage, https://github.com/nanotech-empa/aiida-gaussian
Classifier: Development Status :: 5 - Production/Stable
Classifier: Intended Audience :: Science/Research
Classifier: Natural Language :: English
Classifier: License :: OSI Approved :: MIT License
Classifier: Operating System :: OS Independent
Classifier: Programming Language :: Python :: 3
Classifier: Topic :: Scientific/Engineering :: Chemistry
Classifier: Topic :: Scientific/Engineering :: Physics
Classifier: Topic :: Software Development :: Libraries :: Python Modules
Classifier: Framework :: AiiDA
Requires-Python: >=3.7
License-File: LICENSE
Requires-Dist: aiida-core <3.0.0,>=2.0.0
Requires-Dist: pymatgen >=2022.1.20
Requires-Dist: cclib <=2.0,>=1.8
Requires-Dist: ase
Provides-Extra: dev
Requires-Dist: bumpver ==2022.1119 ; extra == 'dev'
Provides-Extra: pre-commit
Requires-Dist: pre-commit >=2.21.0 ; extra == 'pre-commit'
Provides-Extra: testing
Requires-Dist: pgtest ~=1.3.2 ; extra == 'testing'
Requires-Dist: wheel ~=0.31 ; extra == 'testing'
Requires-Dist: coverage ; extra == 'testing'
Requires-Dist: pytest ~=7.0 ; extra == 'testing'
Requires-Dist: pytest-cov ; extra == 'testing'
Requires-Dist: pytest-regressions ~=2.2 ; extra == 'testing'
Requires-Dist: coveralls ; extra == 'testing'
